koatl_kernel/__init__.py
koatl_kernel/__main__.py
koatl_kernel/kernel.py
koatl_kernel/shell.py
koatl_kernel-1.0.8.data/data/share/jupyter/kernels/koatl/kernel.json
koatl_kernel-1.0.8.dist-info/METADATA
koatl_kernel-1.0.8.dist-info/WHEEL
koatl_kernel-1.0.8.dist-info/licenses/LICENSE
koatl_kernel-1.0.8.dist-info/RECORD
