Metadata-Version: 2.4
Name: koatl-kernel
Version: 1.0.8
Summary: Koatl kernel for Jupyter
Project-URL: Homepage, https://github.com/skkestrel/koatl
Author-email: Kevin <skkestrel@gmail.com>
License: MIT License
License-File: LICENSE
Classifier: Intended Audience :: Developers
Classifier: Programming Language :: Python :: 3
Requires-Python: >=3.8
Requires-Dist: ipykernel
Requires-Dist: jupyter-client
Requires-Dist: jupyter-console
Requires-Dist: koatl
